llm_call/__init__.py
llm_call/llm_call.py
llm_call_msagent-0.1.0.dist-info/METADATA
llm_call_msagent-0.1.0.dist-info/WHEEL
llm_call_msagent-0.1.0.dist-info/top_level.txt
llm_call_msagent-0.1.0.dist-info/RECORD
