Metadata-Version: 2.4
Name: llm-call-msagent
Version: 0.1.0
Summary: Simple Azure OpenAI call helper
Author-email: Your Name <you@example.com>
Project-URL: homepage, https://example.com
Requires-Python: >=3.9
Requires-Dist: python-dotenv
Requires-Dist: azure-identity
Requires-Dist: agent-framework
